quicksong/__init__.py
quicksong/core.py
quicksong/features.cp39-win32.pyd
quicksong/model.py
quicksong/streaming.py
quicksong-0.2.0.dist-info/METADATA
quicksong-0.2.0.dist-info/WHEEL
quicksong-0.2.0.dist-info/top_level.txt
quicksong-0.2.0.dist-info/RECORD
