Metadata-Version: 2.1
Name: quicksong
Version: 0.2.0
Summary: Detect birdsong in long acoustic recordings
Home-page: https://github.com/melizalab/quicksong
Author: Dan Meliza
Author-email: dan@meliza.org
Maintainer: Dan Meliza
Maintainer-email: dan@meliza.org
License: BSD 3-Clause License
Classifier: License :: OSI Approved :: BSD License
Classifier: Programming Language :: Python :: 3
Classifier: Programming Language :: Python :: 3.8
Requires-Python: >=3.8
